codejump/__init__.py
codejump/codejump.py
codejump-0.1.3.dist-info/LICENSE
codejump-0.1.3.dist-info/METADATA
codejump-0.1.3.dist-info/WHEEL
codejump-0.1.3.dist-info/top_level.txt
codejump-0.1.3.dist-info/RECORD
