Metadata-Version: 2.1
Name: codejump
Version: 0.1.3
Summary: A Python library for controlled code jumps using checkpoints and teleportation.
Home-page: https://github.com/Ami-sh/codejump
Author: Ami
Author-email: amishgupta@outlook.com
Classifier: Programming Language :: Python :: 3
Classifier: License :: OSI Approved :: MIT License
Classifier: Operating System :: OS Independent
Requires-Python: >=3.6
License-File: LICENSE
